azure_explorer/__init__.py
azure_explorer/config.py
azure_explorer/managers/__init__.py
azure_explorer/managers/base.py
azure_explorer/managers/container/__init__.py
azure_explorer/managers/container/base.py
azure_explorer/managers/container/blob_storage.py
azure_explorer/managers/container/data_lake.py
azure_explorer/managers/exceptions.py
azure_explorer/managers/models.py
azure_explorer/managers/service_bus.py
azure_explorer/managers/storage_account.py
azure_explorer/managers/subscription.py
azure_explorer/managers/tenant.py
azure_explorer/managers/topic.py
azure_explorer/managers/topic_subscription.py
azure_explorer/managers/utils.py
azure_explorer/short_cuts.py
azure_explorer/widgets/__init__.py
azure_explorer/widgets/app.py
azure_explorer/widgets/components/__init__.py
azure_explorer/widgets/components/azure/__init__.py
azure_explorer/widgets/components/azure/container.py
azure_explorer/widgets/components/azure/service_bus.py
azure_explorer/widgets/components/azure/storage_account.py
azure_explorer/widgets/components/azure/subscription.py
azure_explorer/widgets/components/azure/tenant.py
azure_explorer/widgets/components/windows/__init__.py
azure_explorer/widgets/components/windows/base.py
azure_explorer/widgets/components/windows/browser.py
azure_explorer/widgets/components/windows/selector.py
azure_explorer/widgets/utils.py
azure_explorer-0.6.0.dist-info/METADATA
azure_explorer-0.6.0.dist-info/WHEEL
azure_explorer-0.6.0.dist-info/entry_points.txt
azure_explorer-0.6.0.dist-info/RECORD
